{
    "type": "minecraft:chest",
    "pools": [
        {
            "rolls": 1,
            "entries": [
                {
                    "type": "minecraft:loot_table",
                    "name": "mcbc:armours/leggins/iron",
                    "weight":10             
                },
                {
                    "type": "minecraft:loot_table",
                    "name": "mcbc:armours/leggins/golden",
                    "weight":15                    
                },
                {
                    "type": "minecraft:loot_table",
                    "name": "mcbc:armours/leggins/diamond",
                    "weight":1                    
                },
                {
                    "type": "minecraft:loot_table",
                    "name": "mcbc:armours/leggins/chainmail",
                    "weight":35                    
                },
                {
                    "type": "minecraft:loot_table",
                    "name": "mcbc:armours/leggins/leather",
                    "weight":39                   
                }
            ]
        }
    ]
}